EuclidSearchPackage/__init__.py
EuclidSearchPackage/Demo/WeiboClassV1.py
EuclidSearchPackage/Demo/WeiboClassV2.py
EuclidSearchPackage/Demo/WeiboClassV3.py
EuclidSearchPackage/Demo/__init__.py
EuclidSearchPackage/Utils/EuclidDataTools.py
EuclidSearchPackage/Utils/EuclidDataTools_test.py
EuclidSearchPackage/Utils/MongoClient.py
EuclidSearchPackage/Utils/Set_header.py
EuclidSearchPackage/Utils/Utils.py
EuclidSearchPackage/Utils/__init__.py
EuclidSearchPackage/WeiboSearch/Get_item_url_list.py
EuclidSearchPackage/WeiboSearch/Get_longTextContent.py
EuclidSearchPackage/WeiboSearch/Get_single_weibo_data.py
EuclidSearchPackage/WeiboSearch/Get_single_weibo_details.py
EuclidSearchPackage/WeiboSearch/Get_user_all_weibo.py
EuclidSearchPackage/WeiboSearch/Get_user_info.py
EuclidSearchPackage/WeiboSearch/Set_cookie.py
EuclidSearchPackage/WeiboSearch/__init__.py
Test/DemoTest.py
Test/Test.py
EuclidSearchPackage-0.6.1.dist-info/LICENSE
EuclidSearchPackage-0.6.1.dist-info/METADATA
EuclidSearchPackage-0.6.1.dist-info/WHEEL
EuclidSearchPackage-0.6.1.dist-info/top_level.txt
EuclidSearchPackage-0.6.1.dist-info/RECORD
