Metadata-Version: 2.1
Name: EuclidSearchPackage
Version: 0.6.1
Summary: a package for search data from weibo, zhihu, guba and etc.
Author-email: Euclid Jie <Ouweijie123@outlook.coom>
License: MIT License
Project-URL: Homepage, https://github.com/Euclid-Jie/EuclidSearchPackage
Project-URL: Bug Tracker, https://github.com/Euclid-Jie/EuclidSearchPackage/issues
Classifier: Programming Language :: Python :: 3
Classifier: Operating System :: OS Independent
Requires-Python: >=3.7
License-File: LICENSE
